{
  "default": true,
  "texture": "skillz:textures/gui/sprites/agility.png",
  "attributes": [
    {
      "index": 3,
      "type": "generic.movement_speed",
      "base": 0.09,
      "set_base_value": true,
      "operation": "ADDITION",
      "value": 0.001
    },
    {
      "type": "attribute-backport:player.sneaking_speed",
      "base": 0.2,
      "set_base_value": true,
      "operation": "ADDITION",
      "value": 0.01
    },
    {
      "index": 4,
      "type": "attribute-backport:generic.oxygen_bonus",
      "operation": "ADDITION",
      "value": 0.2
    },
    {
      "type": "attribute-backport:player.submerged_mining_speed",
      "operation": "ADDITION",
      "value": 0.04
    },
    {
      "type": "attribute-backport:generic.water_movement_efficiency",
      "operation": "ADDITION",
      "value": 0.02
    }
  ],
  "bonus": [
    {
      "level": 1,
      "key": "bonusapi:exhaustion_reduction"
    },
    {
      "level": 10,
      "key": "bonusapi:evade_damage"
    },
    {
      "level": 1,
      "key": "bonusapi:fall_damage_reduction"
    }
  ]
}